Metadata-Version: 2.1
Name: hawser
Version: 0.0.1
Summary: 🏷️ Lanyard API Wrapper for Python.
Home-page: https://github.com/5elenay/hawser/
Author: 5elenay
Author-email: 
License: MIT
Project-URL: Bug Tracker, https://github.com/5elenay/hawser/issues
Keywords: lanyard,api,api-wrapper,wrapper,lanyard-python,hawser
Platform: UNKNOWN
Classifier: Development Status :: 5 - Production/Stable
Classifier: Intended Audience :: Developers
Classifier: Operating System :: OS Independent
Classifier: License :: OSI Approved :: MIT License
Classifier: Programming Language :: Python :: 3
Requires-Python: >=3.6.0
